{
  "parent": "klunchbox:any_macaron",
  "criteria": {
    "trigger_acai_macaron": {
      "conditions": {
        "items": [
          {
            "items": [
              "klunchbox:acai_macaron"
            ]
          }
        ]
      },
      "trigger": "minecraft:inventory_changed"
    },
    "trigger_almond_macaron": {
      "conditions": {
        "items": [
          {
            "items": [
              "klunchbox:almond_macaron"
            ]
          }
        ]
      },
      "trigger": "minecraft:inventory_changed"
    },
    "trigger_apple_macaron": {
      "conditions": {
        "items": [
          {
            "items": [
              "klunchbox:apple_macaron"
            ]
          }
        ]
      },
      "trigger": "minecraft:inventory_changed"
    },
    "trigger_banana_macaron": {
      "conditions": {
        "items": [
          {
            "items": [
              "klunchbox:banana_macaron"
            ]
          }
        ]
      },
      "trigger": "minecraft:inventory_changed"
    },
    "trigger_blackberry_macaron": {
      "conditions": {
        "items": [
          {
            "items": [
              "klunchbox:blackberry_macaron"
            ]
          }
        ]
      },
      "trigger": "minecraft:inventory_changed"
    },
    "trigger_blueberry_macaron": {
      "conditions": {
        "items": [
          {
            "items": [
              "klunchbox:blueberry_macaron"
            ]
          }
        ]
      },
      "trigger": "minecraft:inventory_changed"
    },
    "trigger_cake_macaron": {
      "conditions": {
        "items": [
          {
            "items": [
              "klunchbox:cake_macaron"
            ]
          }
        ]
      },
      "trigger": "minecraft:inventory_changed"
    },
    "trigger_caramel_apple_macaron": {
      "conditions": {
        "items": [
          {
            "items": [
              "klunchbox:caramel_apple_macaron"
            ]
          }
        ]
      },
      "trigger": "minecraft:inventory_changed"
    },
    "trigger_caramel_macaron": {
      "conditions": {
        "items": [
          {
            "items": [
              "klunchbox:caramel_macaron"
            ]
          }
        ]
      },
      "trigger": "minecraft:inventory_changed"
    },
    "trigger_carrot_cake_macaron": {
      "conditions": {
        "items": [
          {
            "items": [
              "klunchbox:carrot_cake_macaron"
            ]
          }
        ]
      },
      "trigger": "minecraft:inventory_changed"
    },
    "trigger_cherry_macaron": {
      "conditions": {
        "items": [
          {
            "items": [
              "klunchbox:cherry_macaron"
            ]
          }
        ]
      },
      "trigger": "minecraft:inventory_changed"
    },
    "trigger_chocolate_chip_cookie_macaron": {
      "conditions": {
        "items": [
          {
            "items": [
              "klunchbox:chocolate_chip_cookie_macaron"
            ]
          }
        ]
      },
      "trigger": "minecraft:inventory_changed"
    },
    "trigger_chocolate_macaron": {
      "conditions": {
        "items": [
          {
            "items": [
              "klunchbox:chocolate_macaron"
            ]
          }
        ]
      },
      "trigger": "minecraft:inventory_changed"
    },
    "trigger_chocolate_peanut_butter_macaron": {
      "conditions": {
        "items": [
          {
            "items": [
              "klunchbox:chocolate_peanut_butter_macaron"
            ]
          }
        ]
      },
      "trigger": "minecraft:inventory_changed"
    },
    "trigger_chorus_fruit_macaron": {
      "conditions": {
        "items": [
          {
            "items": [
              "klunchbox:chorus_fruit_macaron"
            ]
          }
        ]
      },
      "trigger": "minecraft:inventory_changed"
    },
    "trigger_cinnamon_roll_macaron": {
      "conditions": {
        "items": [
          {
            "items": [
              "klunchbox:cinnamon_roll_macaron"
            ]
          }
        ]
      },
      "trigger": "minecraft:inventory_changed"
    },
    "trigger_coconut_macaron": {
      "conditions": {
        "items": [
          {
            "items": [
              "klunchbox:coconut_macaron"
            ]
          }
        ]
      },
      "trigger": "minecraft:inventory_changed"
    },
    "trigger_coffee_macaron": {
      "conditions": {
        "items": [
          {
            "items": [
              "klunchbox:coffee_macaron"
            ]
          }
        ]
      },
      "trigger": "minecraft:inventory_changed"
    },
    "trigger_cotton_candy_macaron": {
      "conditions": {
        "items": [
          {
            "items": [
              "klunchbox:cotton_candy_macaron"
            ]
          }
        ]
      },
      "trigger": "minecraft:inventory_changed"
    },
    "trigger_cranberry_macaron": {
      "conditions": {
        "items": [
          {
            "items": [
              "klunchbox:cranberry_macaron"
            ]
          }
        ]
      },
      "trigger": "minecraft:inventory_changed"
    },
    "trigger_diamond_macaron": {
      "conditions": {
        "items": [
          {
            "items": [
              "klunchbox:diamond_macaron"
            ]
          }
        ]
      },
      "trigger": "minecraft:inventory_changed"
    },
    "trigger_donut_macaron": {
      "conditions": {
        "items": [
          {
            "items": [
              "klunchbox:donut_macaron"
            ]
          }
        ]
      },
      "trigger": "minecraft:inventory_changed"
    },
    "trigger_dragon_fruit_macaron": {
      "conditions": {
        "items": [
          {
            "items": [
              "klunchbox:dragon_fruit_macaron"
            ]
          }
        ]
      },
      "trigger": "minecraft:inventory_changed"
    },
    "trigger_egg_macaron": {
      "conditions": {
        "items": [
          {
            "items": [
              "klunchbox:egg_macaron"
            ]
          }
        ]
      },
      "trigger": "minecraft:inventory_changed"
    },
    "trigger_fig_macaron": {
      "conditions": {
        "items": [
          {
            "items": [
              "klunchbox:fig_macaron"
            ]
          }
        ]
      },
      "trigger": "minecraft:inventory_changed"
    },
    "trigger_funfetti_macaron": {
      "conditions": {
        "items": [
          {
            "items": [
              "klunchbox:funfetti_macaron"
            ]
          }
        ]
      },
      "trigger": "minecraft:inventory_changed"
    },
    "trigger_gingerbread_macaron": {
      "conditions": {
        "items": [
          {
            "items": [
              "klunchbox:gingerbread_macaron"
            ]
          }
        ]
      },
      "trigger": "minecraft:inventory_changed"
    },
    "trigger_glow_berry_macaron": {
      "conditions": {
        "items": [
          {
            "items": [
              "klunchbox:glow_berry_macaron"
            ]
          }
        ]
      },
      "trigger": "minecraft:inventory_changed"
    },
    "trigger_golden_macaron": {
      "conditions": {
        "items": [
          {
            "items": [
              "klunchbox:golden_macaron"
            ]
          }
        ]
      },
      "trigger": "minecraft:inventory_changed"
    },
    "trigger_gooseberry_macaron": {
      "conditions": {
        "items": [
          {
            "items": [
              "klunchbox:gooseberry_macaron"
            ]
          }
        ]
      },
      "trigger": "minecraft:inventory_changed"
    },
    "trigger_grape_macaron": {
      "conditions": {
        "items": [
          {
            "items": [
              "klunchbox:grape_macaron"
            ]
          }
        ]
      },
      "trigger": "minecraft:inventory_changed"
    },
    "trigger_honey_macaron": {
      "conditions": {
        "items": [
          {
            "items": [
              "klunchbox:honey_macaron"
            ]
          }
        ]
      },
      "trigger": "minecraft:inventory_changed"
    },
    "trigger_kiwi_macaron": {
      "conditions": {
        "items": [
          {
            "items": [
              "klunchbox:kiwi_macaron"
            ]
          }
        ]
      },
      "trigger": "minecraft:inventory_changed"
    },
    "trigger_lemon_macaron": {
      "conditions": {
        "items": [
          {
            "items": [
              "klunchbox:lemon_macaron"
            ]
          }
        ]
      },
      "trigger": "minecraft:inventory_changed"
    },
    "trigger_lime_macaron": {
      "conditions": {
        "items": [
          {
            "items": [
              "klunchbox:lime_macaron"
            ]
          }
        ]
      },
      "trigger": "minecraft:inventory_changed"
    },
    "trigger_lychee_macaron": {
      "conditions": {
        "items": [
          {
            "items": [
              "klunchbox:lychee_macaron"
            ]
          }
        ]
      },
      "trigger": "minecraft:inventory_changed"
    },
    "trigger_mango_macaron": {
      "conditions": {
        "items": [
          {
            "items": [
              "klunchbox:mango_macaron"
            ]
          }
        ]
      },
      "trigger": "minecraft:inventory_changed"
    },
    "trigger_mangosteen_macaron": {
      "conditions": {
        "items": [
          {
            "items": [
              "klunchbox:mangosteen_macaron"
            ]
          }
        ]
      },
      "trigger": "minecraft:inventory_changed"
    },
    "trigger_matcha_macaron": {
      "conditions": {
        "items": [
          {
            "items": [
              "klunchbox:matcha_macaron"
            ]
          }
        ]
      },
      "trigger": "minecraft:inventory_changed"
    },
    "trigger_mint_chocolate_macaron": {
      "conditions": {
        "items": [
          {
            "items": [
              "klunchbox:mint_chocolate_macaron"
            ]
          }
        ]
      },
      "trigger": "minecraft:inventory_changed"
    },
    "trigger_mint_macaron": {
      "conditions": {
        "items": [
          {
            "items": [
              "klunchbox:mint_macaron"
            ]
          }
        ]
      },
      "trigger": "minecraft:inventory_changed"
    },
    "trigger_mocha_macaron": {
      "conditions": {
        "items": [
          {
            "items": [
              "klunchbox:mocha_macaron"
            ]
          }
        ]
      },
      "trigger": "minecraft:inventory_changed"
    },
    "trigger_neapolitan_macaron": {
      "conditions": {
        "items": [
          {
            "items": [
              "klunchbox:neapolitan_macaron"
            ]
          }
        ]
      },
      "trigger": "minecraft:inventory_changed"
    },
    "trigger_orange_macaron": {
      "conditions": {
        "items": [
          {
            "items": [
              "klunchbox:orange_macaron"
            ]
          }
        ]
      },
      "trigger": "minecraft:inventory_changed"
    },
    "trigger_oreo_macaron": {
      "conditions": {
        "items": [
          {
            "items": [
              "klunchbox:oreo_macaron"
            ]
          }
        ]
      },
      "trigger": "minecraft:inventory_changed"
    },
    "trigger_passion_fruit_macaron": {
      "conditions": {
        "items": [
          {
            "items": [
              "klunchbox:passion_fruit_macaron"
            ]
          }
        ]
      },
      "trigger": "minecraft:inventory_changed"
    },
    "trigger_peach_macaron": {
      "conditions": {
        "items": [
          {
            "items": [
              "klunchbox:peach_macaron"
            ]
          }
        ]
      },
      "trigger": "minecraft:inventory_changed"
    },
    "trigger_peanut_butter_jelly_macaron": {
      "conditions": {
        "items": [
          {
            "items": [
              "klunchbox:peanut_butter_jelly_macaron"
            ]
          }
        ]
      },
      "trigger": "minecraft:inventory_changed"
    },
    "trigger_peanut_butter_macaron": {
      "conditions": {
        "items": [
          {
            "items": [
              "klunchbox:peanut_butter_macaron"
            ]
          }
        ]
      },
      "trigger": "minecraft:inventory_changed"
    },
    "trigger_pear_macaron": {
      "conditions": {
        "items": [
          {
            "items": [
              "klunchbox:pear_macaron"
            ]
          }
        ]
      },
      "trigger": "minecraft:inventory_changed"
    },
    "trigger_pecan_pie_macaron": {
      "conditions": {
        "items": [
          {
            "items": [
              "klunchbox:pecan_pie_macaron"
            ]
          }
        ]
      },
      "trigger": "minecraft:inventory_changed"
    },
    "trigger_peppermint_macaron": {
      "conditions": {
        "items": [
          {
            "items": [
              "klunchbox:peppermint_macaron"
            ]
          }
        ]
      },
      "trigger": "minecraft:inventory_changed"
    },
    "trigger_pina_colada_macaron": {
      "conditions": {
        "items": [
          {
            "items": [
              "klunchbox:pina_colada_macaron"
            ]
          }
        ]
      },
      "trigger": "minecraft:inventory_changed"
    },
    "trigger_pineapple_macaron": {
      "conditions": {
        "items": [
          {
            "items": [
              "klunchbox:pineapple_macaron"
            ]
          }
        ]
      },
      "trigger": "minecraft:inventory_changed"
    },
    "trigger_plum_macaron": {
      "conditions": {
        "items": [
          {
            "items": [
              "klunchbox:plum_macaron"
            ]
          }
        ]
      },
      "trigger": "minecraft:inventory_changed"
    },
    "trigger_pomegranate_macaron": {
      "conditions": {
        "items": [
          {
            "items": [
              "klunchbox:pomegranate_macaron"
            ]
          }
        ]
      },
      "trigger": "minecraft:inventory_changed"
    },
    "trigger_pumpkin_macaron": {
      "conditions": {
        "items": [
          {
            "items": [
              "klunchbox:pumpkin_macaron"
            ]
          }
        ]
      },
      "trigger": "minecraft:inventory_changed"
    },
    "trigger_raspberry_macaron": {
      "conditions": {
        "items": [
          {
            "items": [
              "klunchbox:raspberry_macaron"
            ]
          }
        ]
      },
      "trigger": "minecraft:inventory_changed"
    },
    "trigger_rose_macaron": {
      "conditions": {
        "items": [
          {
            "items": [
              "klunchbox:rose_macaron"
            ]
          }
        ]
      },
      "trigger": "minecraft:inventory_changed"
    },
    "trigger_smores_macaron": {
      "conditions": {
        "items": [
          {
            "items": [
              "klunchbox:smores_macaron"
            ]
          }
        ]
      },
      "trigger": "minecraft:inventory_changed"
    },
    "trigger_snowman_macaron": {
      "conditions": {
        "items": [
          {
            "items": [
              "klunchbox:snowman_macaron"
            ]
          }
        ]
      },
      "trigger": "minecraft:inventory_changed"
    },
    "trigger_starfruit_macaron": {
      "conditions": {
        "items": [
          {
            "items": [
              "klunchbox:starfruit_macaron"
            ]
          }
        ]
      },
      "trigger": "minecraft:inventory_changed"
    },
    "trigger_strawberry_macaron": {
      "conditions": {
        "items": [
          {
            "items": [
              "klunchbox:strawberry_macaron"
            ]
          }
        ]
      },
      "trigger": "minecraft:inventory_changed"
    },
    "trigger_sweet_berry_macaron": {
      "conditions": {
        "items": [
          {
            "items": [
              "klunchbox:sweet_berry_macaron"
            ]
          }
        ]
      },
      "trigger": "minecraft:inventory_changed"
    },
    "trigger_tiramisu_macaron": {
      "conditions": {
        "items": [
          {
            "items": [
              "klunchbox:tiramisu_macaron"
            ]
          }
        ]
      },
      "trigger": "minecraft:inventory_changed"
    },
    "trigger_vanilla_macaron": {
      "conditions": {
        "items": [
          {
            "items": [
              "klunchbox:vanilla_macaron"
            ]
          }
        ]
      },
      "trigger": "minecraft:inventory_changed"
    },
    "trigger_watermelon_macaron": {
      "conditions": {
        "items": [
          {
            "items": [
              "klunchbox:watermelon_macaron"
            ]
          }
        ]
      },
      "trigger": "minecraft:inventory_changed"
    }
  },
  "display": {
    "announce_to_chat": true,
    "description": {
      "text": "Craft every type of macaron"
    },
    "frame": "challenge",
    "hidden": false,
    "icon": {
      "item": "klunchbox:pecan_pie_macaron"
    },
    "show_toast": true,
    "title": {
      "text": "Every Macaron"
    }
  },
  "requirements": [
    [
      "trigger_lychee_macaron"
    ],
    [
      "trigger_rose_macaron"
    ],
    [
      "trigger_raspberry_macaron"
    ],
    [
      "trigger_strawberry_macaron"
    ],
    [
      "trigger_neapolitan_macaron"
    ],
    [
      "trigger_mangosteen_macaron"
    ],
    [
      "trigger_dragon_fruit_macaron"
    ],
    [
      "trigger_pomegranate_macaron"
    ],
    [
      "trigger_cranberry_macaron"
    ],
    [
      "trigger_sweet_berry_macaron"
    ],
    [
      "trigger_apple_macaron"
    ],
    [
      "trigger_caramel_apple_macaron"
    ],
    [
      "trigger_cherry_macaron"
    ],
    [
      "trigger_orange_macaron"
    ],
    [
      "trigger_pumpkin_macaron"
    ],
    [
      "trigger_gooseberry_macaron"
    ],
    [
      "trigger_mango_macaron"
    ],
    [
      "trigger_glow_berry_macaron"
    ],
    [
      "trigger_peach_macaron"
    ],
    [
      "trigger_pear_macaron"
    ],
    [
      "trigger_banana_macaron"
    ],
    [
      "trigger_egg_macaron"
    ],
    [
      "trigger_honey_macaron"
    ],
    [
      "trigger_starfruit_macaron"
    ],
    [
      "trigger_pineapple_macaron"
    ],
    [
      "trigger_lemon_macaron"
    ],
    [
      "trigger_golden_macaron"
    ],
    [
      "trigger_lime_macaron"
    ],
    [
      "trigger_mint_macaron"
    ],
    [
      "trigger_mint_chocolate_macaron"
    ],
    [
      "trigger_kiwi_macaron"
    ],
    [
      "trigger_watermelon_macaron"
    ],
    [
      "trigger_matcha_macaron"
    ],
    [
      "trigger_grape_macaron"
    ],
    [
      "trigger_blueberry_macaron"
    ],
    [
      "trigger_diamond_macaron"
    ],
    [
      "trigger_plum_macaron"
    ],
    [
      "trigger_blackberry_macaron"
    ],
    [
      "trigger_passion_fruit_macaron"
    ],
    [
      "trigger_fig_macaron"
    ],
    [
      "trigger_acai_macaron"
    ],
    [
      "trigger_chorus_fruit_macaron"
    ],
    [
      "trigger_chocolate_macaron"
    ],
    [
      "trigger_chocolate_peanut_butter_macaron"
    ],
    [
      "trigger_cake_macaron"
    ],
    [
      "trigger_gingerbread_macaron"
    ],
    [
      "trigger_coffee_macaron"
    ],
    [
      "trigger_mocha_macaron"
    ],
    [
      "trigger_chocolate_chip_cookie_macaron"
    ],
    [
      "trigger_tiramisu_macaron"
    ],
    [
      "trigger_smores_macaron"
    ],
    [
      "trigger_peanut_butter_jelly_macaron"
    ],
    [
      "trigger_peanut_butter_macaron"
    ],
    [
      "trigger_pecan_pie_macaron"
    ],
    [
      "trigger_caramel_macaron"
    ],
    [
      "trigger_almond_macaron"
    ],
    [
      "trigger_coconut_macaron"
    ],
    [
      "trigger_vanilla_macaron"
    ],
    [
      "trigger_snowman_macaron"
    ],
    [
      "trigger_peppermint_macaron"
    ],
    [
      "trigger_oreo_macaron"
    ],
    [
      "trigger_funfetti_macaron"
    ],
    [
      "trigger_pina_colada_macaron"
    ],
    [
      "trigger_cinnamon_roll_macaron"
    ],
    [
      "trigger_carrot_cake_macaron"
    ],
    [
      "trigger_donut_macaron"
    ],
    [
      "trigger_cotton_candy_macaron"
    ]
  ]
}